ChainLibrary/__init__.py
ChainLibrary/keywords.py
robotframework_chainlibrary-2023.11.dist-info/LICENSE
robotframework_chainlibrary-2023.11.dist-info/METADATA
robotframework_chainlibrary-2023.11.dist-info/WHEEL
robotframework_chainlibrary-2023.11.dist-info/top_level.txt
robotframework_chainlibrary-2023.11.dist-info/RECORD
