Metadata-Version: 2.1
Name: robotframework-chainlibrary
Version: 2023.11
Summary: Robot Framework library for running keywords in chain
Author-email: Mauricio Gutierrez <103621275+crsdet@users.noreply.github.com>
License: GNU GENERAL PUBLIC LICENSE
Project-URL: Homepage, https://github.com/crsdet/robotframework-chainlibrary
Project-URL: Documentation, https://crsdet.github.io/robotframework-chainlibrary/
Keywords: robotframework
Classifier: Framework :: Robot Framework :: Library
Requires-Python: >=3.8
License-File: LICENSE
Requires-Dist: robotframework
